robotdriver
