Metadata-Version: 1.0
Name: RobotDriver
Version: 0.2.3
Summary: RobotFramework support for Bitten
Home-page: http://bitbucket.org/xyb/robotdriver
Author: Xie Yanbo
Author-email: xieyanbo@gmail.com
License: New BSD
Keywords: trac,bitten,robotframework,pybot,test
Platform: Linux
Platform: Unix
Platform: Windows
Platform: MacOS X
Classifier: Development Status :: 3 - Alpha
Classifier: Programming Language :: Python
Classifier: Framework :: Trac
Classifier: Operating System :: OS Independent
Classifier: License :: OSI Approved :: BSD License
Classifier: Natural Language :: English
